s3tree/__init__.py
s3tree/__version__.py
s3tree/core.py
s3tree/exceptions.py
s3tree/models.py
s3tree/types.py
s3tree/utils.py
s3tree-0.3.0.dist-info/METADATA
s3tree-0.3.0.dist-info/RECORD
s3tree-0.3.0.dist-info/WHEEL
s3tree-0.3.0.dist-info/top_level.txt
