Metadata-Version: 2.1
Name: s3tree
Version: 0.3.0
Summary: Access S3 objects like tree.
Home-page: https://github.com/sanketsaurav/s3tree
Author: Sanket Saurav
Author-email: sanketsaurav@gmail.com
License: MIT
Platform: UNKNOWN
Classifier: Development Status :: 3 - Alpha
Classifier: Intended Audience :: Developers
Classifier: License :: OSI Approved :: MIT License
Classifier: Natural Language :: English
Classifier: Programming Language :: Python
Classifier: Programming Language :: Python :: 2
Classifier: Programming Language :: Python :: 2.7
Classifier: Programming Language :: Python :: 3
Classifier: Programming Language :: Python :: 3.4
Classifier: Programming Language :: Python :: 3.5
Classifier: Programming Language :: Python :: 3.6
Classifier: Programming Language :: Python :: Implementation :: CPython
Classifier: Programming Language :: Python :: Implementation :: PyPy
Requires-Python: >=2.7.0
Requires-Dist: boto3
Requires-Dist: future
Requires-Dist: mimelib
Requires-Dist: six
